medvol/__init__.py
medvol/medvol.py
medvol-0.0.18.dist-info/licenses/LICENSE
medvol-0.0.18.dist-info/METADATA
medvol-0.0.18.dist-info/WHEEL
medvol-0.0.18.dist-info/top_level.txt
medvol-0.0.18.dist-info/RECORD
